{
  "state": "COMPLETE",
  "task_description": "Setup monitoring dashboard",
  "workflow_id": "de27d70c",
  "questions": null,
  "answers": {},
  "plan": {
    "task_summary": "Implement persistence",
    "approach": "Use selected DB",
    "assumptions": [
      "Networking available"
    ],
    "steps": [
      {
        "id": "S1",
        "description": "Set up schema",
        "rationale": "Foundation",
        "dependencies": [],
        "estimated_duration": "10 minutes",
        "validation_criteria": [
          "Schema applied"
        ],
        "risks": [
          "Permissions"
        ],
        "rollback_strategy": "Drop schema"
      }
    ],
    "success_criteria": [
      "DB reachable"
    ],
    "risks": [
      "Secrets storage"
    ],
    "estimated_total_duration": "10 minutes",
    "confidence": 88
  },
  "execution_log": [],
  "metadata": {
    "task_context": {},
    "created_at": "2025-11-08T23:42:25.191127",
    "state_durations": {
      "INIT": 0.001,
      "ANALYZING": 0.029,
      "PLANNING": 0.094,
      "VALIDATING": 0.002
    },
    "last_updated": "2025-11-08T23:42:25.346669",
    "analysis": {
      "task_clarity_score": 60,
      "technical_completeness_score": 50,
      "should_ask_questions": true,
      "identified_gaps": [
        "Need environment details"
      ],
      "assumptions_made": [],
      "next_state": "QUESTIONING",
      "reasoning": "Missing DB selection"
    },
    "assumptions": []
  }
}